{
  "info": {
    "name": "NetPilot Backend API",
    "description": "Complete API collection for NetPilot Backend authentication system",
    "schema": "https://schema.getpostman.com/json/collection/v2.1.0/collection.json"
  },
  "variable": [
    {
      "key": "baseUrl",
      "value": "http://localhost:3000/api",
      "type": "string"
    },
    {
      "key": "accessToken",
      "value": "",
      "type": "string"
    }
  ],
  "item": [
    {
      "name": "Authentication",
      "item": [
        {
          "name": "Register User",
          "event": [
            {
              "listen": "test",
              "script": {
                "exec": [
                  "pm.test(\"Status code is 201\", function () {",
                  "    pm.response.to.have.status(201);",
                  "});",
                  "",
                  "pm.test(\"Response has access_token\", function () {",
                  "    var jsonData = pm.response.json();",
                  "    pm.expect(jsonData).to.have.property('access_token');",
                  "    pm.environment.set(\"accessToken\", jsonData.access_token);",
                  "});",
                  "",
                  "pm.test(\"Response has user data\", function () {",
                  "    var jsonData = pm.response.json();",
                  "    pm.expect(jsonData).to.have.property('user');",
                  "    pm.expect(jsonData.user).to.have.property('email');",
                  "    pm.expect(jsonData.user).to.have.property('username');",
                  "});"
                ],
                "type": "text/javascript"
              }
            }
          ],
          "request": {
            "method": "POST",
            "header": [
              {
                "key": "Content-Type",
                "value": "application/json"
              }
            ],
            "body": {
              "mode": "raw",
              "raw": "{\n  \"email\": \"john.doe@example.com\",\n  \"username\": \"johndoe\",\n  \"password\": \"SecurePass123!\",\n  \"firstName\": \"John\",\n  \"lastName\": \"Doe\"\n}"
            },
            "url": {
              "raw": "{{baseUrl}}/auth/register",
              "host": ["{{baseUrl}}"],
              "path": ["auth", "register"]
            }
          }
        },
        {
          "name": "Login User",
          "event": [
            {
              "listen": "test",
              "script": {
                "exec": [
                  "pm.test(\"Status code is 200\", function () {",
                  "    pm.response.to.have.status(200);",
                  "});",
                  "",
                  "pm.test(\"Response has access_token\", function () {",
                  "    var jsonData = pm.response.json();",
                  "    pm.expect(jsonData).to.have.property('access_token');",
                  "    pm.environment.set(\"accessToken\", jsonData.access_token);",
                  "});"
                ],
                "type": "text/javascript"
              }
            }
          ],
          "request": {
            "method": "POST",
            "header": [
              {
                "key": "Content-Type",
                "value": "application/json"
              }
            ],
            "body": {
              "mode": "raw",
              "raw": "{\n  \"usernameOrEmail\": \"john.doe@example.com\",\n  \"password\": \"SecurePass123!\"\n}"
            },
            "url": {
              "raw": "{{baseUrl}}/auth/login",
              "host": ["{{baseUrl}}"],
              "path": ["auth", "login"]
            }
          }
        },
        {
          "name": "Get User Profile",
          "event": [
            {
              "listen": "test",
              "script": {
                "exec": [
                  "pm.test(\"Status code is 200\", function () {",
                  "    pm.response.to.have.status(200);",
                  "});",
                  "",
                  "pm.test(\"Response has user data\", function () {",
                  "    var jsonData = pm.response.json();",
                  "    pm.expect(jsonData).to.have.property('email');",
                  "    pm.expect(jsonData).to.have.property('username');",
                  "});"
                ],
                "type": "text/javascript"
              }
            }
          ],
          "request": {
            "method": "GET",
            "header": [
              {
                "key": "Authorization",
                "value": "Bearer {{accessToken}}"
              },
              {
                "key": "Content-Type",
                "value": "application/json"
              }
            ],
            "url": {
              "raw": "{{baseUrl}}/auth/profile",
              "host": ["{{baseUrl}}"],
              "path": ["auth", "profile"]
            }
          }
        },
        {
          "name": "Logout User",
          "event": [
            {
              "listen": "test",
              "script": {
                "exec": [
                  "pm.test(\"Status code is 200\", function () {",
                  "    pm.response.to.have.status(200);",
                  "});",
                  "",
                  "pm.test(\"Response has success message\", function () {",
                  "    var jsonData = pm.response.json();",
                  "    pm.expect(jsonData).to.have.property('message');",
                  "});"
                ],
                "type": "text/javascript"
              }
            }
          ],
          "request": {
            "method": "POST",
            "header": [
              {
                "key": "Authorization",
                "value": "Bearer {{accessToken}}"
              },
              {
                "key": "Content-Type",
                "value": "application/json"
              }
            ],
            "url": {
              "raw": "{{baseUrl}}/auth/logout",
              "host": ["{{baseUrl}}"],
              "path": ["auth", "logout"]
            }
          }
        }
      ]
    },
    {
      "name": "Users",
      "item": [
        {
          "name": "Get Current User",
          "event": [
            {
              "listen": "test",
              "script": {
                "exec": [
                  "pm.test(\"Status code is 200\", function () {",
                  "    pm.response.to.have.status(200);",
                  "});",
                  "",
                  "pm.test(\"Response has user data\", function () {",
                  "    var jsonData = pm.response.json();",
                  "    pm.expect(jsonData).to.have.property('email');",
                  "    pm.expect(jsonData).to.have.property('username');",
                  "});"
                ],
                "type": "text/javascript"
              }
            }
          ],
          "request": {
            "method": "GET",
            "header": [
              {
                "key": "Authorization",
                "value": "Bearer {{accessToken}}"
              },
              {
                "key": "Content-Type",
                "value": "application/json"
              }
            ],
            "url": {
              "raw": "{{baseUrl}}/users/me",
              "host": ["{{baseUrl}}"],
              "path": ["users", "me"]
            }
          }
        }
      ]
    },
    {
      "name": "Validation Tests",
      "item": [
        {
          "name": "Register - Invalid Email",
          "event": [
            {
              "listen": "test",
              "script": {
                "exec": [
                  "pm.test(\"Status code is 400\", function () {",
                  "    pm.response.to.have.status(400);",
                  "});",
                  "",
                  "pm.test(\"Response has validation errors\", function () {",
                  "    var jsonData = pm.response.json();",
                  "    pm.expect(jsonData).to.have.property('message');",
                  "    pm.expect(jsonData.message).to.be.an('array');",
                  "});"
                ],
                "type": "text/javascript"
              }
            }
          ],
          "request": {
            "method": "POST",
            "header": [
              {
                "key": "Content-Type",
                "value": "application/json"
              }
            ],
            "body": {
              "mode": "raw",
              "raw": "{\n  \"email\": \"invalid-email\",\n  \"username\": \"testuser\",\n  \"password\": \"Test123!@#\"\n}"
            },
            "url": {
              "raw": "{{baseUrl}}/auth/register",
              "host": ["{{baseUrl}}"],
              "path": ["auth", "register"]
            }
          }
        },
        {
          "name": "Register - Weak Password",
          "event": [
            {
              "listen": "test",
              "script": {
                "exec": [
                  "pm.test(\"Status code is 400\", function () {",
                  "    pm.response.to.have.status(400);",
                  "});",
                  "",
                  "pm.test(\"Response has password validation errors\", function () {",
                  "    var jsonData = pm.response.json();",
                  "    pm.expect(jsonData).to.have.property('message');",
                  "    pm.expect(jsonData.message).to.be.an('array');",
                  "});"
                ],
                "type": "text/javascript"
              }
            }
          ],
          "request": {
            "method": "POST",
            "header": [
              {
                "key": "Content-Type",
                "value": "application/json"
              }
            ],
            "body": {
              "mode": "raw",
              "raw": "{\n  \"email\": \"test@example.com\",\n  \"username\": \"testuser\",\n  \"password\": \"weak\"\n}"
            },
            "url": {
              "raw": "{{baseUrl}}/auth/register",
              "host": ["{{baseUrl}}"],
              "path": ["auth", "register"]
            }
          }
        },
        {
          "name": "Login - Invalid Credentials",
          "event": [
            {
              "listen": "test",
              "script": {
                "exec": [
                  "pm.test(\"Status code is 401\", function () {",
                  "    pm.response.to.have.status(401);",
                  "});",
                  "",
                  "pm.test(\"Response has error message\", function () {",
                  "    var jsonData = pm.response.json();",
                  "    pm.expect(jsonData).to.have.property('message');",
                  "});"
                ],
                "type": "text/javascript"
              }
            }
          ],
          "request": {
            "method": "POST",
            "header": [
              {
                "key": "Content-Type",
                "value": "application/json"
              }
            ],
            "body": {
              "mode": "raw",
              "raw": "{\n  \"usernameOrEmail\": \"john.doe@example.com\",\n  \"password\": \"wrongpassword\"\n}"
            },
            "url": {
              "raw": "{{baseUrl}}/auth/login",
              "host": ["{{baseUrl}}"],
              "path": ["auth", "login"]
            }
          }
        },
        {
          "name": "Protected Route - No Token",
          "event": [
            {
              "listen": "test",
              "script": {
                "exec": [
                  "pm.test(\"Status code is 401\", function () {",
                  "    pm.response.to.have.status(401);",
                  "});",
                  "",
                  "pm.test(\"Response has unauthorized error\", function () {",
                  "    var jsonData = pm.response.json();",
                  "    pm.expect(jsonData).to.have.property('statusCode', 401);",
                  "});"
                ],
                "type": "text/javascript"
              }
            }
          ],
          "request": {
            "method": "GET",
            "header": [
              {
                "key": "Content-Type",
                "value": "application/json"
              }
            ],
            "url": {
              "raw": "{{baseUrl}}/auth/profile",
              "host": ["{{baseUrl}}"],
              "path": ["auth", "profile"]
            }
          }
        }
      ]
    }
  ]
}
